Workbook

Sheet Leggimi
A1: Orvane Table · cruscotto del fondatore
A2: Generato da tools/foglio_kpi.py (npm run foglio). Riferimenti: Parti 3.6, 8.6 e 15 del prompt master.
A4: Come si usa
A5: Celle gialle | B5: da compilare: numeri della settimana, del mese, contatti e clienti
A6: Testo blu | B6: valori inseriti a mano: obiettivi, soglie, listino. Si possono cambiare
A7: Testo nero | B7: formule: non scriverci sopra
A8: Testo verde | B8: valori presi da un altro foglio
A9: Celle rosse | B9: sotto soglia: si corregge prima l'indicatore più a sinistra (Parte 15.5)
A11: Ogni venerdì (10 minuti) | B11: riga della settimana in Settimana; prima cella rossa da sinistra; prompt 17.14 se serve
A12: Ogni sera | B12: Contatti: filtrare la colonna Scaduta e fare le azioni del giorno
A13: Primo venerdì del mese | B13: riga del mese in Mese; se la differenza dal modello supera il 30%, aggiornare il modello (15.5)
A15: Regole di lettura | B15: una settimana bassa è rumore, due di fila sono un segnale; nessun cambio di prezzo con meno di 10 osservazioni
A16: Righe di esempio | B16: la prima riga di Contatti e di Clienti è un esempio con dati inventati: cancellatela quando inserite i vostri

Sheet Obiettivi
A1: Obiettivi e soglie
A2: Valori della Parte 15.1 e del modello della Parte 10 (scenario realistico). Si possono cambiare: tutte le formule li leggono da qui.
A4: Indicatore settimanale | B4: Obiettivo | C4: Soglia di allarme | D4: Azione se sotto soglia
A5: Contatti qualificati | B5: 14 | C5: 8 | D5: Bloccare fasce orarie in agenda, allargare la lista
A6: Conversazioni | B6: 4 | C6: 2 | D6: Cambiare apertura (Parte 9.1)
A7: Demo | B7: 2 | C7: 1 | D7: Rendere la demo più veloce: pronta in 24 ore
A8: Proposte | B8: 1 | C8: 0.5 | D8: Rivedere la qualificazione (allarme: 0 per due settimane)
A9: Ore di vendita (massimo) | B9: 16 | C9: 20 | D9: Oltre la soglia per tre settimane: più segnalazioni e partner
A10: Conversione contatti-contratti | B10: 0.045 | C10: 0.02 | D10: Sotto il 2% su 60 contatti: analisi dei motivi di perdita
A12: Modello di riferimento, scenario realistico (Parte 10.5)
A13: Mese | B13: Periodo | C13: Contratti firmati | D13: Clienti attivi a fine mese | E13: Ricorrente incassato (€) | F13: Cassa cumulata (€)
A14: 1 | B14: nov 2026 | C14: 0 | D14: 0 | E14: 0 | F14: 0
A15: 2 | B15: dic 2026 | C15: 2 | D15: 2 | E15: 0 | F15: 158
A16: 3 | B16: gen 2027 | C16: 1 | D16: 3 | E16: 221 | F16: 544
A17: 4 | B17: feb 2027 | C17: 2 | D17: 4.9 | E17: 322 | F17: 1221
A18: 5 | B18: mar 2027 | C18: 2 | D18: 6.8 | E18: 526 | F18: 2361
A19: 6 | B19: apr 2027 | C19: 2 | D19: 8.6 | E19: 725 | F19: 3596
A20: 7 | B20: mag 2027 | C20: 3 | D20: 11.3 | E20: 917 | F20: 5126
A21: 8 | B21: giu 2027 | C21: 3 | D21: 14 | E21: 1212 | F21: 7041
A22: 9 | B22: lug 2027 | C22: 3 | D22: 16.5 | E22: 1497 | F22: 9092
A23: 10 | B23: ago 2027 | C23: 3 | D23: 19 | E23: 1773 | F23: 11275
A24: 11 | B24: set 2027 | C24: 3 | D24: 21.5 | E24: 2042 | F24: 13587
A25: 12 | B25: ott 2027 | C25: 3 | D25: 23.8 | E25: 2302 | F25: 15964
A26: Fonte: tabella 10.5 del prompt master; ricalcolabile con npm run modello. Se il primo incasso slitta, spostare i periodi di un mese (Parte 8.9).

Sheet Listino
A1: Listino
A2: Prezzi indicativi al netto di IVA (Parte 4.1), da validare nelle prime dieci conversazioni. Il canone non si abbassa mai (4.6).
A4: Pacchetto | B4: Setup (€) | C4: Canone mensile (€) | D4: Costo variabile stimato (€/mese) | E4: Minuti inclusi | F4: Margine mensile (€) | G4: Margine %
A5: Start | B5: 290 | C5: 49 | D5: 3 | E5: 0 | F5: =C5-D5 -> 46 | G5: =IFERROR(F5/C5,0) -> 0.93877551
A6: Pro | B6: 790 | C6: 129 | D6: 30 | E6: 250 | F6: =C6-D6 -> 99 | G6: =IFERROR(F6/C6,0) -> 0.76744186
A7: Premium | B7: 1490 | C7: 219 | D7: 65 | E7: 500 | F7: =C7-D7 -> 154 | G7: =IFERROR(F7/C7,0) -> 0.70319635
A9: Minuto extra (€) | B9: 0.25
A10: Sconto cliente fondatore | B10: 0.5
A11: Fonte: Parte 4 del prompt master; stesso listino di src/modello/listino.ts.

Sheet Contatti
A1: Contatti
A2: Una riga per locale. Criteri: 1 = vero, 0 = falso, vuoto = da verificare. Punteggio ≥ 7: demo entro una settimana; 4-6: un messaggio al mese; sotto 4: archiviare (Parte 3.6).
A4: Locale | B4: Indirizzo | C4: Telefono | D4: Titolare | E4: Segmento | F4: Titolare decide da solo | G4: Almeno 30 coperti | H4: Prenotazioni per telefono | I4: Ammette chiamate perse | J4: Sito o scheda Google trascurati | K4: Usa WhatsApp per prenotare | L4: Più di 20 coperti a sera | M4: Tavoli o sale per gruppi | N4: Aperto da più di 3 anni | O4: Contatto personale | P4: Punteggio | Q4: Da verificare | R4: Cosa fare | S4: Primo contatto | T4: Canale | U4: Esito | V4: Prossima azione | W4: Data prossima azione | X4: Scaduta | Y4: Pacchetto proposto | Z4: Canone proposto (€) | AA4: Note | AB4: Motivo della perdita
A5: Trattoria Esempio (riga di prova) | B5: Via Roma 1, Città | C5: +39 0000 000000 | D5: Mario | E5: Ristorante 30-120 | F5: 1 | G5: 1 | H5: 1 | I5: 1 | K5: 1 | L5: 1 | M5: 0 | N5: 1 | O5: 0 | P5: =IF(COUNTA(A5)=0,"",COUNTIF(F5:O5,1)) -> 7 | Q5: =IF(COUNTA(A5)=0,"",COUNTBLANK(F5:O5)) -> 1 | R5: =IF(P5="","",IF(P5>=7,"Demo entro una settimana",IF(P5>=4,"Un messaggio al mese","Archiviare"))) -> Demo entro una settimana | S5: 46330 | T5: Visita | U5: Conversazione | V5: Preparare demo sul suo menu | W5: 46332 | X5: =IF(AND(ISNUMBER(W5),W5<TODAY()),"SÌ","") | Y5: Pro | Z5: =IF(Y5="","",IFERROR(INDEX(Listino!$C$5:$C$7,MATCH(Y5,Listino!$A$5:$A$7,0)),"")) -> 129 | AA5: Perde "4-5 chiamate il sabato sera" (parole del titolare)
P6: =IF(COUNTA(A6)=0,"",COUNTIF(F6:O6,1)) | Q6: =IF(COUNTA(A6)=0,"",COUNTBLANK(F6:O6)) | R6: =IF(P6="","",IF(P6>=7,"Demo entro una settimana",IF(P6>=4,"Un messaggio al mese","Archiviare"))) | X6: =IF(AND(ISNUMBER(W6),W6<TODAY()),"SÌ","") | Z6: =IF(Y6="","",IFERROR(INDEX(Listino!$C$5:$C$7,MATCH(Y6,Listino!$A$5:$A$7,0)),""))
P7: =IF(COUNTA(A7)=0,"",COUNTIF(F7:O7,1)) | Q7: =IF(COUNTA(A7)=0,"",COUNTBLANK(F7:O7)) | R7: =IF(P7="","",IF(P7>=7,"Demo entro una settimana",IF(P7>=4,"Un messaggio al mese","Archiviare"))) | X7: =IF(AND(ISNUMBER(W7),W7<TODAY()),"SÌ","") | Z7: =IF(Y7="","",IFERROR(INDEX(Listino!$C$5:$C$7,MATCH(Y7,Listino!$A$5:$A$7,0)),""))
P8: =IF(COUNTA(A8)=0,"",COUNTIF(F8:O8,1)) | Q8: =IF(COUNTA(A8)=0,"",COUNTBLANK(F8:O8)) | R8: =IF(P8="","",IF(P8>=7,"Demo entro una settimana",IF(P8>=4,"Un messaggio al mese","Archiviare"))) | X8: =IF(AND(ISNUMBER(W8),W8<TODAY()),"SÌ","") | Z8: =IF(Y8="","",IFERROR(INDEX(Listino!$C$5:$C$7,MATCH(Y8,Listino!$A$5:$A$7,0)),""))
P9: =IF(COUNTA(A9)=0,"",COUNTIF(F9:O9,1)) | Q9: =IF(COUNTA(A9)=0,"",COUNTBLANK(F9:O9)) | R9: =IF(P9="","",IF(P9>=7,"Demo entro una settimana",IF(P9>=4,"Un messaggio al mese","Archiviare"))) | X9: =IF(AND(ISNUMBER(W9),W9<TODAY()),"SÌ","") | Z9: =IF(Y9="","",IFERROR(INDEX(Listino!$C$5:$C$7,MATCH(Y9,Listino!$A$5:$A$7,0)),""))
P10: =IF(COUNTA(A10)=0,"",COUNTIF(F10:O10,1)) | Q10: =IF(COUNTA(A10)=0,"",COUNTBLANK(F10:O10)) | R10: =IF(P10="","",IF(P10>=7,"Demo entro una settimana",IF(P10>=4,"Un messaggio al mese","Archiviare"))) | X10: =IF(AND(ISNUMBER(W10),W10<TODAY()),"SÌ","") | Z10: =IF(Y10="","",IFERROR(INDEX(Listino!$C$5:$C$7,MATCH(Y10,Listino!$A$5:$A$7,0)),""))
P11: =IF(COUNTA(A11)=0,"",COUNTIF(F11:O11,1)) | Q11: =IF(COUNTA(A11)=0,"",COUNTBLANK(F11:O11)) | R11: =IF(P11="","",IF(P11>=7,"Demo entro una settimana",IF(P11>=4,"Un messaggio al mese","Archiviare"))) | X11: =IF(AND(ISNUMBER(W11),W11<TODAY()),"SÌ","") | Z11: =IF(Y11="","",IFERROR(INDEX(Listino!$C$5:$C$7,MATCH(Y11,Listino!$A$5:$A$7,0)),""))
P12: =IF(COUNTA(A12)=0,"",COUNTIF(F12:O12,1)) | Q12: =IF(COUNTA(A12)=0,"",COUNTBLANK(F12:O12)) | R12: =IF(P12="","",IF(P12>=7,"Demo entro una settimana",IF(P12>=4,"Un messaggio al mese","Archiviare"))) | X12: =IF(AND(ISNUMBER(W12),W12<TODAY()),"SÌ","") | Z12: =IF(Y12="","",IFERROR(INDEX(Listino!$C$5:$C$7,MATCH(Y12,Listino!$A$5:$A$7,0)),""))
P13: =IF(COUNTA(A13)=0,"",COUNTIF(F13:O13,1)) | Q13: =IF(COUNTA(A13)=0,"",COUNTBLANK(F13:O13)) | R13: =IF(P13="","",IF(P13>=7,"Demo entro una settimana",IF(P13>=4,"Un messaggio al mese","Archiviare"))) | X13: =IF(AND(ISNUMBER(W13),W13<TODAY()),"SÌ","") | Z13: =IF(Y13="","",IFERROR(INDEX(Listino!$C$5:$C$7,MATCH(Y13,Listino!$A$5:$A$7,0)),""))
P14: =IF(COUNTA(A14)=0,"",COUNTIF(F14:O14,1)) | Q14: =IF(COUNTA(A14)=0,"",COUNTBLANK(F14:O14)) | R14: =IF(P14="","",IF(P14>=7,"Demo entro una settimana",IF(P14>=4,"Un messaggio al mese","Archiviare"))) | X14: =IF(AND(ISNUMBER(W14),W14<TODAY()),"SÌ","") | Z14: =IF(Y14="","",IFERROR(INDEX(Listino!$C$5:$C$7,MATCH(Y14,Listino!$A$5:$A$7,0)),""))
P15: =IF(COUNTA(A15)=0,"",COUNTIF(F15:O15,1)) | Q15: =IF(COUNTA(A15)=0,"",COUNTBLANK(F15:O15)) | R15: =IF(P15="","",IF(P15>=7,"Demo entro una settimana",IF(P15>=4,"Un messaggio al mese","Archiviare"))) | X15: =IF(AND(ISNUMBER(W15),W15<TODAY()),"SÌ","") | Z15: =IF(Y15="","",IFERROR(INDEX(Listino!$C$5:$C$7,MATCH(Y15,Listino!$A$5:$A$7,0)),""))
P16: =IF(COUNTA(A16)=0,"",COUNTIF(F16:O16,1)) | Q16: =IF(COUNTA(A16)=0,"",COUNTBLANK(F16:O16)) | R16: =IF(P16="","",IF(P16>=7,"Demo entro una settimana",IF(P16>=4,"Un messaggio al mese","Archiviare"))) | X16: =IF(AND(ISNUMBER(W16),W16<TODAY()),"SÌ","") | Z16: =IF(Y16="","",IFERROR(INDEX(Listino!$C$5:$C$7,MATCH(Y16,Listino!$A$5:$A$7,0)),""))
P17: =IF(COUNTA(A17)=0,"",COUNTIF(F17:O17,1)) | Q17: =IF(COUNTA(A17)=0,"",COUNTBLANK(F17:O17)) | R17: =IF(P17="","",IF(P17>=7,"Demo entro una settimana",IF(P17>=4,"Un messaggio al mese","Archiviare"))) | X17: =IF(AND(ISNUMBER(W17),W17<TODAY()),"SÌ","") | Z17: =IF(Y17="","",IFERROR(INDEX(Listino!$C$5:$C$7,MATCH(Y17,Listino!$A$5:$A$7,0)),""))
... P104: =IF(COUNTA(A104)=0,"",COUNTIF(F104:O104,1)) | Q104: =IF(COUNTA(A104)=0,"",COUNTBLANK(F104:O104)) | R104: =IF(P104="","",IF(P104>=7,"Demo entro una settimana",IF(P104>=4,"Un messaggio al mese","Archiviare"))) | X104: =IF(AND(ISNUMBER(W104),W104<TODAY()),"SÌ","") | Z104: =IF(Y104="","",IFERROR(INDEX(Listino!$C$5:$C$7,MATCH(Y104,Listino!$A$5:$A$7,0)),""))

Sheet Settimana
A1: Settimana
A2: Una riga per settimana, compilata il venerdì. Rosso = sotto soglia; SEGNALE = due settimane consecutive sotto soglia nei contatti (Parte 15.5).
A4: N. | B4: Dal (lunedì) | C4: Contatti | D4: Conversazioni | E4: Demo | F4: Proposte | G4: Contratti | H4: Ore di vendita | I4: Cassa (€) | J4: Conversione cumulata | K4: Contatti cumulati | L4: Segnale contatti | M4: Note: cosa è andato storto, tre obiettivi
A5: 1 | B5: 46321 | J5: =IF(SUM($C$5:C5)=0,"",SUM($G$5:G5)/SUM($C$5:C5)) | K5: =IF(COUNT(C5)=0,"",SUM($C$5:C5)) | L5: =""
A6: 2 | B6: 46328 | J6: =IF(SUM($C$5:C6)=0,"",SUM($G$5:G6)/SUM($C$5:C6)) | K6: =IF(COUNT(C6)=0,"",SUM($C$5:C6)) | L6: =IF(AND(COUNT(C6)=1,COUNT(C5)=1),IF(AND(C6<Obiettivi!$C$5,C5<Obiettivi!$C$5),"SEGNALE",""),"")
A7: 3 | B7: 46335 | J7: =IF(SUM($C$5:C7)=0,"",SUM($G$5:G7)/SUM($C$5:C7)) | K7: =IF(COUNT(C7)=0,"",SUM($C$5:C7)) | L7: =IF(AND(COUNT(C7)=1,COUNT(C6)=1),IF(AND(C7<Obiettivi!$C$5,C6<Obiettivi!$C$5),"SEGNALE",""),"")
A8: 4 | B8: 46342 | J8: =IF(SUM($C$5:C8)=0,"",SUM($G$5:G8)/SUM($C$5:C8)) | K8: =IF(COUNT(C8)=0,"",SUM($C$5:C8)) | L8: =IF(AND(COUNT(C8)=1,COUNT(C7)=1),IF(AND(C8<Obiettivi!$C$5,C7<Obiettivi!$C$5),"SEGNALE",""),"")
A9: 5 | B9: 46349 | J9: =IF(SUM($C$5:C9)=0,"",SUM($G$5:G9)/SUM($C$5:C9)) | K9: =IF(COUNT(C9)=0,"",SUM($C$5:C9)) | L9: =IF(AND(COUNT(C9)=1,COUNT(C8)=1),IF(AND(C9<Obiettivi!$C$5,C8<Obiettivi!$C$5),"SEGNALE",""),"")
A10: 6 | B10: 46356 | J10: =IF(SUM($C$5:C10)=0,"",SUM($G$5:G10)/SUM($C$5:C10)) | K10: =IF(COUNT(C10)=0,"",SUM($C$5:C10)) | L10: =IF(AND(COUNT(C10)=1,COUNT(C9)=1),IF(AND(C10<Obiettivi!$C$5,C9<Obiettivi!$C$5),"SEGNALE",""),"")
A11: 7 | B11: 46363 | J11: =IF(SUM($C$5:C11)=0,"",SUM($G$5:G11)/SUM($C$5:C11)) | K11: =IF(COUNT(C11)=0,"",SUM($C$5:C11)) | L11: =IF(AND(COUNT(C11)=1,COUNT(C10)=1),IF(AND(C11<Obiettivi!$C$5,C10<Obiettivi!$C$5),"SEGNALE",""),"")
A12: 8 | B12: 46370 | J12: =IF(SUM($C$5:C12)=0,"",SUM($G$5:G12)/SUM($C$5:C12)) | K12: =IF(COUNT(C12)=0,"",SUM($C$5:C12)) | L12: =IF(AND(COUNT(C12)=1,COUNT(C11)=1),IF(AND(C12<Obiettivi!$C$5,C11<Obiettivi!$C$5),"SEGNALE",""),"")
A13: 9 | B13: 46377 | J13: =IF(SUM($C$5:C13)=0,"",SUM($G$5:G13)/SUM($C$5:C13)) | K13: =IF(COUNT(C13)=0,"",SUM($C$5:C13)) | L13: =IF(AND(COUNT(C13)=1,COUNT(C12)=1),IF(AND(C13<Obiettivi!$C$5,C12<Obiettivi!$C$5),"SEGNALE",""),"")
A14: 10 | B14: 46384 | J14: =IF(SUM($C$5:C14)=0,"",SUM($G$5:G14)/SUM($C$5:C14)) | K14: =IF(COUNT(C14)=0,"",SUM($C$5:C14)) | L14: =IF(AND(COUNT(C14)=1,COUNT(C13)=1),IF(AND(C14<Obiettivi!$C$5,C13<Obiettivi!$C$5),"SEGNALE",""),"")
A15: 11 | B15: 46391 | J15: =IF(SUM($C$5:C15)=0,"",SUM($G$5:G15)/SUM($C$5:C15)) | K15: =IF(COUNT(C15)=0,"",SUM($C$5:C15)) | L15: =IF(AND(COUNT(C15)=1,COUNT(C14)=1),IF(AND(C15<Obiettivi!$C$5,C14<Obiettivi!$C$5),"SEGNALE",""),"")
A16: 12 | B16: 46398 | J16: =IF(SUM($C$5:C16)=0,"",SUM($G$5:G16)/SUM($C$5:C16)) | K16: =IF(COUNT(C16)=0,"",SUM($C$5:C16)) | L16: =IF(AND(COUNT(C16)=1,COUNT(C15)=1),IF(AND(C16<Obiettivi!$C$5,C15<Obiettivi!$C$5),"SEGNALE",""),"")
A17: 13 | B17: 46405 | J17: =IF(SUM($C$5:C17)=0,"",SUM($G$5:G17)/SUM($C$5:C17)) | K17: =IF(COUNT(C17)=0,"",SUM($C$5:C17)) | L17: =IF(AND(COUNT(C17)=1,COUNT(C16)=1),IF(AND(C17<Obiettivi!$C$5,C16<Obiettivi!$C$5),"SEGNALE",""),"")
... A56: 52 | B56: 46678 | J56: =IF(SUM($C$5:C56)=0,"",SUM($G$5:G56)/SUM($C$5:C56)) | K56: =IF(COUNT(C56)=0,"",SUM($C$5:C56)) | L56: =IF(AND(COUNT(C56)=1,COUNT(C55)=1),IF(AND(C56<Obiettivi!$C$5,C55<Obiettivi!$C$5),"SEGNALE",""),"")

Sheet Mese
A1: Mese
A2: Primo venerdì del mese. Obiettivi dal foglio Obiettivi; rosso = sotto il 70% dell'obiettivo o oltre la soglia della Parte 15.2-15.3.
A4: Mese | B4: Periodo | C4: Clienti a inizio mese | D4: Clienti persi | E4: Clienti a fine mese | F4: Ricorrente incassato (€) | G4: Costi variabili (€) | H4: Cassa cumulata (€) | I4: Fatture scadute > 15 gg | J4: Ricavo medio per cliente | K4: Margine lordo | L4: Abbandono mensile | M4: Clienti: % obiettivo | N4: Ricorrente: % obiettivo | O4: Cassa: % obiettivo | P4: Risolte senza persona | Q4: Domande aperte | R4: Ore medie di correzione | S4: Minuti usati / inclusi | T4: Giorni di attivazione (media) | U4: Soddisfazione (0-10)
A5: 1 | B5: nov 2026 | J5: =IF(OR(COUNT(F5)=0,COUNT(E5)=0,E5=0),"",F5/E5) | K5: =IF(OR(COUNT(F5)=0,F5=0),"",(F5-G5)/F5) | L5: =IF(OR(COUNT(C5)=0,C5=0,COUNT(D5)=0),"",D5/C5) | M5: =IF(OR(COUNT(E5)=0,Obiettivi!$D$14=0),"",E5/Obiettivi!$D$14) | N5: =IF(OR(COUNT(F5)=0,Obiettivi!$E$14=0),"",F5/Obiettivi!$E$14) | O5: =IF(OR(COUNT(H5)=0,Obiettivi!$F$14=0),"",H5/Obiettivi!$F$14)
A6: 2 | B6: dic 2026 | J6: =IF(OR(COUNT(F6)=0,COUNT(E6)=0,E6=0),"",F6/E6) | K6: =IF(OR(COUNT(F6)=0,F6=0),"",(F6-G6)/F6) | L6: =IF(OR(COUNT(C6)=0,C6=0,COUNT(D6)=0),"",D6/C6) | M6: =IF(OR(COUNT(E6)=0,Obiettivi!$D$15=0),"",E6/Obiettivi!$D$15) | N6: =IF(OR(COUNT(F6)=0,Obiettivi!$E$15=0),"",F6/Obiettivi!$E$15) | O6: =IF(OR(COUNT(H6)=0,Obiettivi!$F$15=0),"",H6/Obiettivi!$F$15)
A7: 3 | B7: gen 2027 | J7: =IF(OR(COUNT(F7)=0,COUNT(E7)=0,E7=0),"",F7/E7) | K7: =IF(OR(COUNT(F7)=0,F7=0),"",(F7-G7)/F7) | L7: =IF(OR(COUNT(C7)=0,C7=0,COUNT(D7)=0),"",D7/C7) | M7: =IF(OR(COUNT(E7)=0,Obiettivi!$D$16=0),"",E7/Obiettivi!$D$16) | N7: =IF(OR(COUNT(F7)=0,Obiettivi!$E$16=0),"",F7/Obiettivi!$E$16) | O7: =IF(OR(COUNT(H7)=0,Obiettivi!$F$16=0),"",H7/Obiettivi!$F$16)
A8: 4 | B8: feb 2027 | J8: =IF(OR(COUNT(F8)=0,COUNT(E8)=0,E8=0),"",F8/E8) | K8: =IF(OR(COUNT(F8)=0,F8=0),"",(F8-G8)/F8) | L8: =IF(OR(COUNT(C8)=0,C8=0,COUNT(D8)=0),"",D8/C8) | M8: =IF(OR(COUNT(E8)=0,Obiettivi!$D$17=0),"",E8/Obiettivi!$D$17) | N8: =IF(OR(COUNT(F8)=0,Obiettivi!$E$17=0),"",F8/Obiettivi!$E$17) | O8: =IF(OR(COUNT(H8)=0,Obiettivi!$F$17=0),"",H8/Obiettivi!$F$17)
A9: 5 | B9: mar 2027 | J9: =IF(OR(COUNT(F9)=0,COUNT(E9)=0,E9=0),"",F9/E9) | K9: =IF(OR(COUNT(F9)=0,F9=0),"",(F9-G9)/F9) | L9: =IF(OR(COUNT(C9)=0,C9=0,COUNT(D9)=0),"",D9/C9) | M9: =IF(OR(COUNT(E9)=0,Obiettivi!$D$18=0),"",E9/Obiettivi!$D$18) | N9: =IF(OR(COUNT(F9)=0,Obiettivi!$E$18=0),"",F9/Obiettivi!$E$18) | O9: =IF(OR(COUNT(H9)=0,Obiettivi!$F$18=0),"",H9/Obiettivi!$F$18)
A10: 6 | B10: apr 2027 | J10: =IF(OR(COUNT(F10)=0,COUNT(E10)=0,E10=0),"",F10/E10) | K10: =IF(OR(COUNT(F10)=0,F10=0),"",(F10-G10)/F10) | L10: =IF(OR(COUNT(C10)=0,C10=0,COUNT(D10)=0),"",D10/C10) | M10: =IF(OR(COUNT(E10)=0,Obiettivi!$D$19=0),"",E10/Obiettivi!$D$19) | N10: =IF(OR(COUNT(F10)=0,Obiettivi!$E$19=0),"",F10/Obiettivi!$E$19) | O10: =IF(OR(COUNT(H10)=0,Obiettivi!$F$19=0),"",H10/Obiettivi!$F$19)
A11: 7 | B11: mag 2027 | J11: =IF(OR(COUNT(F11)=0,COUNT(E11)=0,E11=0),"",F11/E11) | K11: =IF(OR(COUNT(F11)=0,F11=0),"",(F11-G11)/F11) | L11: =IF(OR(COUNT(C11)=0,C11=0,COUNT(D11)=0),"",D11/C11) | M11: =IF(OR(COUNT(E11)=0,Obiettivi!$D$20=0),"",E11/Obiettivi!$D$20) | N11: =IF(OR(COUNT(F11)=0,Obiettivi!$E$20=0),"",F11/Obiettivi!$E$20) | O11: =IF(OR(COUNT(H11)=0,Obiettivi!$F$20=0),"",H11/Obiettivi!$F$20)
A12: 8 | B12: giu 2027 | J12: =IF(OR(COUNT(F12)=0,COUNT(E12)=0,E12=0),"",F12/E12) | K12: =IF(OR(COUNT(F12)=0,F12=0),"",(F12-G12)/F12) | L12: =IF(OR(COUNT(C12)=0,C12=0,COUNT(D12)=0),"",D12/C12) | M12: =IF(OR(COUNT(E12)=0,Obiettivi!$D$21=0),"",E12/Obiettivi!$D$21) | N12: =IF(OR(COUNT(F12)=0,Obiettivi!$E$21=0),"",F12/Obiettivi!$E$21) | O12: =IF(OR(COUNT(H12)=0,Obiettivi!$F$21=0),"",H12/Obiettivi!$F$21)
A13: 9 | B13: lug 2027 | J13: =IF(OR(COUNT(F13)=0,COUNT(E13)=0,E13=0),"",F13/E13) | K13: =IF(OR(COUNT(F13)=0,F13=0),"",(F13-G13)/F13) | L13: =IF(OR(COUNT(C13)=0,C13=0,COUNT(D13)=0),"",D13/C13) | M13: =IF(OR(COUNT(E13)=0,Obiettivi!$D$22=0),"",E13/Obiettivi!$D$22) | N13: =IF(OR(COUNT(F13)=0,Obiettivi!$E$22=0),"",F13/Obiettivi!$E$22) | O13: =IF(OR(COUNT(H13)=0,Obiettivi!$F$22=0),"",H13/Obiettivi!$F$22)
A14: 10 | B14: ago 2027 | J14: =IF(OR(COUNT(F14)=0,COUNT(E14)=0,E14=0),"",F14/E14) | K14: =IF(OR(COUNT(F14)=0,F14=0),"",(F14-G14)/F14) | L14: =IF(OR(COUNT(C14)=0,C14=0,COUNT(D14)=0),"",D14/C14) | M14: =IF(OR(COUNT(E14)=0,Obiettivi!$D$23=0),"",E14/Obiettivi!$D$23) | N14: =IF(OR(COUNT(F14)=0,Obiettivi!$E$23=0),"",F14/Obiettivi!$E$23) | O14: =IF(OR(COUNT(H14)=0,Obiettivi!$F$23=0),"",H14/Obiettivi!$F$23)
A15: 11 | B15: set 2027 | J15: =IF(OR(COUNT(F15)=0,COUNT(E15)=0,E15=0),"",F15/E15) | K15: =IF(OR(COUNT(F15)=0,F15=0),"",(F15-G15)/F15) | L15: =IF(OR(COUNT(C15)=0,C15=0,COUNT(D15)=0),"",D15/C15) | M15: =IF(OR(COUNT(E15)=0,Obiettivi!$D$24=0),"",E15/Obiettivi!$D$24) | N15: =IF(OR(COUNT(F15)=0,Obiettivi!$E$24=0),"",F15/Obiettivi!$E$24) | O15: =IF(OR(COUNT(H15)=0,Obiettivi!$F$24=0),"",H15/Obiettivi!$F$24)
A16: 12 | B16: ott 2027 | J16: =IF(OR(COUNT(F16)=0,COUNT(E16)=0,E16=0),"",F16/E16) | K16: =IF(OR(COUNT(F16)=0,F16=0),"",(F16-G16)/F16) | L16: =IF(OR(COUNT(C16)=0,C16=0,COUNT(D16)=0),"",D16/C16) | M16: =IF(OR(COUNT(E16)=0,Obiettivi!$D$25=0),"",E16/Obiettivi!$D$25) | N16: =IF(OR(COUNT(F16)=0,Obiettivi!$E$25=0),"",F16/Obiettivi!$E$25) | O16: =IF(OR(COUNT(H16)=0,Obiettivi!$F$25=0),"",H16/Obiettivi!$F$25)
A18: Soglie (Parte 15.2-15.3): ricavo medio sotto 85 €; margine sotto 65%; abbandono sopra 5% (segnale se per due mesi); clienti e ricorrente sotto il 70% dell'obiettivo; cassa sotto il 60%; più di una fattura scaduta; risolte sotto 60%; più di 15 domande aperte; correzioni oltre 72 ore; minuti oltre 110%; attivazione oltre 8 giorni; soddisfazione sotto 7.

Sheet Clienti
A1: Clienti
A2: Una riga per cliente attivo. Canone e minuti inclusi arrivano dal Listino. Rosso: minuti oltre il 110% o rischio alto (Parte 13.6).
A4: Locale | B4: Pacchetto | C4: Data di attivazione | D4: Canone (€) | E4: Minuti inclusi | F4: Minuti usati nel mese | G4: Uso dei minuti | H4: Mesi consecutivi oltre limite | I4: Ultimo contatto | J4: Giorni dall'ultimo contatto | K4: Rischio di abbandono | L4: Prossima azione | M4: Note
A5: Trattoria Esempio (riga di prova) | B5: Pro | C5: 46367 | D5: =IF(B5="","",IFERROR(INDEX(Listino!$C$5:$C$7,MATCH(B5,Listino!$A$5:$A$7,0)),"")) -> 129 | E5: =IF(B5="","",IFERROR(INDEX(Listino!$E$5:$E$7,MATCH(B5,Listino!$A$5:$A$7,0)),"")) -> 250 | F5: 180 | G5: =IF(OR(COUNT(F5)=0,COUNT(E5)=0),"",IF(E5=0,"",F5/E5)) -> 0.72 | H5: 0 | I5: 46374 | J5: =IF(AND(ISNUMBER(I5),I5<=TODAY()),TODAY()-I5,"") | K5: basso | L5: Chiamata del giorno 30 | M5: Cliente fondatore
D6: =IF(B6="","",IFERROR(INDEX(Listino!$C$5:$C$7,MATCH(B6,Listino!$A$5:$A$7,0)),"")) | E6: =IF(B6="","",IFERROR(INDEX(Listino!$E$5:$E$7,MATCH(B6,Listino!$A$5:$A$7,0)),"")) | G6: =IF(OR(COUNT(F6)=0,COUNT(E6)=0),"",IF(E6=0,"",F6/E6)) | J6: =IF(AND(ISNUMBER(I6),I6<=TODAY()),TODAY()-I6,"")
D7: =IF(B7="","",IFERROR(INDEX(Listino!$C$5:$C$7,MATCH(B7,Listino!$A$5:$A$7,0)),"")) | E7: =IF(B7="","",IFERROR(INDEX(Listino!$E$5:$E$7,MATCH(B7,Listino!$A$5:$A$7,0)),"")) | G7: =IF(OR(COUNT(F7)=0,COUNT(E7)=0),"",IF(E7=0,"",F7/E7)) | J7: =IF(AND(ISNUMBER(I7),I7<=TODAY()),TODAY()-I7,"")
D8: =IF(B8="","",IFERROR(INDEX(Listino!$C$5:$C$7,MATCH(B8,Listino!$A$5:$A$7,0)),"")) | E8: =IF(B8="","",IFERROR(INDEX(Listino!$E$5:$E$7,MATCH(B8,Listino!$A$5:$A$7,0)),"")) | G8: =IF(OR(COUNT(F8)=0,COUNT(E8)=0),"",IF(E8=0,"",F8/E8)) | J8: =IF(AND(ISNUMBER(I8),I8<=TODAY()),TODAY()-I8,"")
D9: =IF(B9="","",IFERROR(INDEX(Listino!$C$5:$C$7,MATCH(B9,Listino!$A$5:$A$7,0)),"")) | E9: =IF(B9="","",IFERROR(INDEX(Listino!$E$5:$E$7,MATCH(B9,Listino!$A$5:$A$7,0)),"")) | G9: =IF(OR(COUNT(F9)=0,COUNT(E9)=0),"",IF(E9=0,"",F9/E9)) | J9: =IF(AND(ISNUMBER(I9),I9<=TODAY()),TODAY()-I9,"")
D10: =IF(B10="","",IFERROR(INDEX(Listino!$C$5:$C$7,MATCH(B10,Listino!$A$5:$A$7,0)),"")) | E10: =IF(B10="","",IFERROR(INDEX(Listino!$E$5:$E$7,MATCH(B10,Listino!$A$5:$A$7,0)),"")) | G10: =IF(OR(COUNT(F10)=0,COUNT(E10)=0),"",IF(E10=0,"",F10/E10)) | J10: =IF(AND(ISNUMBER(I10),I10<=TODAY()),TODAY()-I10,"")
D11: =IF(B11="","",IFERROR(INDEX(Listino!$C$5:$C$7,MATCH(B11,Listino!$A$5:$A$7,0)),"")) | E11: =IF(B11="","",IFERROR(INDEX(Listino!$E$5:$E$7,MATCH(B11,Listino!$A$5:$A$7,0)),"")) | G11: =IF(OR(COUNT(F11)=0,COUNT(E11)=0),"",IF(E11=0,"",F11/E11)) | J11: =IF(AND(ISNUMBER(I11),I11<=TODAY()),TODAY()-I11,"")
D12: =IF(B12="","",IFERROR(INDEX(Listino!$C$5:$C$7,MATCH(B12,Listino!$A$5:$A$7,0)),"")) | E12: =IF(B12="","",IFERROR(INDEX(Listino!$E$5:$E$7,MATCH(B12,Listino!$A$5:$A$7,0)),"")) | G12: =IF(OR(COUNT(F12)=0,COUNT(E12)=0),"",IF(E12=0,"",F12/E12)) | J12: =IF(AND(ISNUMBER(I12),I12<=TODAY()),TODAY()-I12,"")
D13: =IF(B13="","",IFERROR(INDEX(Listino!$C$5:$C$7,MATCH(B13,Listino!$A$5:$A$7,0)),"")) | E13: =IF(B13="","",IFERROR(INDEX(Listino!$E$5:$E$7,MATCH(B13,Listino!$A$5:$A$7,0)),"")) | G13: =IF(OR(COUNT(F13)=0,COUNT(E13)=0),"",IF(E13=0,"",F13/E13)) | J13: =IF(AND(ISNUMBER(I13),I13<=TODAY()),TODAY()-I13,"")
D14: =IF(B14="","",IFERROR(INDEX(Listino!$C$5:$C$7,MATCH(B14,Listino!$A$5:$A$7,0)),"")) | E14: =IF(B14="","",IFERROR(INDEX(Listino!$E$5:$E$7,MATCH(B14,Listino!$A$5:$A$7,0)),"")) | G14: =IF(OR(COUNT(F14)=0,COUNT(E14)=0),"",IF(E14=0,"",F14/E14)) | J14: =IF(AND(ISNUMBER(I14),I14<=TODAY()),TODAY()-I14,"")
D15: =IF(B15="","",IFERROR(INDEX(Listino!$C$5:$C$7,MATCH(B15,Listino!$A$5:$A$7,0)),"")) | E15: =IF(B15="","",IFERROR(INDEX(Listino!$E$5:$E$7,MATCH(B15,Listino!$A$5:$A$7,0)),"")) | G15: =IF(OR(COUNT(F15)=0,COUNT(E15)=0),"",IF(E15=0,"",F15/E15)) | J15: =IF(AND(ISNUMBER(I15),I15<=TODAY()),TODAY()-I15,"")
D16: =IF(B16="","",IFERROR(INDEX(Listino!$C$5:$C$7,MATCH(B16,Listino!$A$5:$A$7,0)),"")) | E16: =IF(B16="","",IFERROR(INDEX(Listino!$E$5:$E$7,MATCH(B16,Listino!$A$5:$A$7,0)),"")) | G16: =IF(OR(COUNT(F16)=0,COUNT(E16)=0),"",IF(E16=0,"",F16/E16)) | J16: =IF(AND(ISNUMBER(I16),I16<=TODAY()),TODAY()-I16,"")
D17: =IF(B17="","",IFERROR(INDEX(Listino!$C$5:$C$7,MATCH(B17,Listino!$A$5:$A$7,0)),"")) | E17: =IF(B17="","",IFERROR(INDEX(Listino!$E$5:$E$7,MATCH(B17,Listino!$A$5:$A$7,0)),"")) | G17: =IF(OR(COUNT(F17)=0,COUNT(E17)=0),"",IF(E17=0,"",F17/E17)) | J17: =IF(AND(ISNUMBER(I17),I17<=TODAY()),TODAY()-I17,"")
... D44: =IF(B44="","",IFERROR(INDEX(Listino!$C$5:$C$7,MATCH(B44,Listino!$A$5:$A$7,0)),"")) | E44: =IF(B44="","",IFERROR(INDEX(Listino!$E$5:$E$7,MATCH(B44,Listino!$A$5:$A$7,0)),"")) | G44: =IF(OR(COUNT(F44)=0,COUNT(E44)=0),"",IF(E44=0,"",F44/E44)) | J44: =IF(AND(ISNUMBER(I44),I44<=TODAY()),TODAY()-I44,"")

Sheet Concorrenti
A1: Concorrenti
A2: Ricerca del 24/10/2026 (docs/ricerca/concorrenti.md). Aggiornare ogni trimestre e aggiungere quelli locali.
A4: Nome | B4: Cosa offre | C4: Prezzo | D4: Durata contratto | E4: Punto debole | F4: Fonte | G4: Verificato il
A5: Fonio | B5: Assistente telefonico AI, anche ristoranti | C5: Solo 119 €/mese (99 € annuale) 1.000 minuti; Team 359 €/mese; extra 0,10-0,12 €/min | D5: Non indicata | E5: Da configurare da sé, nessuna persona locale | F5: https://www.fonio.ai/it/prezzi/ | G5: 46319
A6: CloudTalk AI Receptionist | B6: Receptionist AI su centralino cloud | C6: Da 99 €/mese per 200 minuti + 25 €/utente; extra 0,50 €/min | D6: Non verificata | E6: Costo per minuto alto, generico | F6: https://www.cloudtalk.io/it/blog/quanto-costa-servizio-risposta-ia/ | G6: 46319
A7: Retell AI | B7: Piattaforma per agenti vocali | C7: 0,07-0,31 $/min a consumo | D7: Nessun minimo | E7: Strumento per sviluppatori | F7: https://www.retellai.com/pricing | G7: 46319
A8: ElevenLabs Agents | B8: Piattaforma vocale (nostro fornitore) | C8: 0,08 $/min; 15 minuti gratis | D8: A consumo | E8: Fornitore, non concorrente diretto | F8: https://elevenlabs.io/pricing/api | G8: 46319
A9: Ainora | B9: Receptionist AI per ristoranti | C9: Non pubblicato | D9: Non indicata | E9: Dati elaborati anche negli USA di default | F9: https://ainora.lt/it/receptionist-ai-ristoranti | G9: 46319
A10: Chiama.ai | B10: Centralino AI (Verona) | C10: Non pubblicato | D10: Non indicata | E10: Dichiarazione AI dal primo contatto: non verificato | F10: https://www.chiama.ai | G10: 46319
A11: Cosmio | B11: Automazioni; receptionist AI open source | C11: Non pubblicato | D11: Non indicata | E11: Il receptionist si presenta con nome da persona | F11: https://cosmio.it | G11: 46319
A12: TheFork Manager | B12: Prenotazioni + portale | C12: Non pubblicato in Italia; stima indiretta Francia ~139 €/mese + 2-4 €/coperto | D12: Non verificata | E12: Commissione per coperto | F12: https://restaurant.eatapp.co/en/blog/best-restaurant-reservation-software-france | G12: 46319
A13: Zenchef | B13: Prenotazioni, sito, CRM | C13: Non pubblicato; indiretto ~150 €/mese medio | D13: Non verificata | E13: Non risponde al telefono | F13: https://www.businesscoot.com/en/company/zenchef | G13: 46319
A14: CoverManager | B14: Prenotazioni e CRM | C14: Non pubblicato | D14: Non verificata | E14: Pensato anche per catene | F14: https://www.capterra.it/software/1012086/covermanager | G14: 46319
A15: TeamSystem Cassa in Cloud | B15: Cassa e gestionale | C15: Non visibile; TS Scontrini + RT 30 € + IVA/mese annuale | D15: Annuale (TS Scontrini) | E15: Non risponde al telefono | F15: https://www.teamsystem.com/horeca/cassa-in-cloud/prezzi/ | G15: 46319
